my_termo/__init__.py
my_termo/main.py
my_termo/raffle.py
my_termo/words.json
my_termo-0.2.0.dist-info/entry_points.txt
my_termo-0.2.0.dist-info/LICENSE
my_termo-0.2.0.dist-info/WHEEL
my_termo-0.2.0.dist-info/METADATA
my_termo-0.2.0.dist-info/RECORD
