Metadata-Version: 2.1
Name: my-termo
Version: 0.2.0
Summary: A simple termo in command line style
Home-page: https://github.com/GussSoares/my-termo
Keywords: termo,command-line
Author: Gustavo Soares
Author-email: gustavo.soares.cdc@gmail.com
Requires-Python: >=3.8,<4.0
Classifier: Operating System :: OS Independent
Classifier: Programming Language :: Python :: 3
Classifier: Programming Language :: Python :: 3.10
Classifier: Programming Language :: Python :: 3.8
Classifier: Programming Language :: Python :: 3.9
Classifier: Topic :: Software Development :: Libraries :: Python Modules
Requires-Dist: colorama (>=0.4.4,<0.5.0)
Project-URL: Repository, https://github.com/GussSoares/my-termo
